<Tournament_Data>
	<Match>
		<MatchID>01</MatchID>
		<MatchTitle>Winners Finals</MatchTitle>
		<Games>
			<Game>
				<GameID>1</GameID>
				<Team1>
					<Player1>Thgblaster</Player1>
					<Class1>Class_Icons\Artillerist.png</Class1>
					<Player2>Hashiro</Player2>
					<Class2>Class_Icons\Gunslinger.png</Class2>
					<Player3>Geoxx</Player3>
					<Class3>Class_Icons\Bard.png</Class3>
				</Team1>
				<Team2>
					<Player1>Suke</Player1>
					<Class1>Class_Icons\Shadowhunter.png</Class1>
					<Player2>Solistalia</Player2>
					<Class2>Class_Icons\Wardancer.png</Class2>
					<Player3>Riesa</Player3>
					<Class3>Class_Icons\Bard.png</Class3>
				</Team2>
			</Game>
			<Game>
				<GameID>2</GameID>
				<Team1>
					<Player1></Player1>
					<Class1></Class1>
					<Player2></Player2>
					<Class2></Class2>
					<Player3></Player3>
					<Class3></Class3>
				</Team1>
				<Team2>
					<Player1></Player1>
					<Class1></Class1>
					<Player2></Player2>
					<Class2></Class2>
					<Player3></Player3>
					<Class3></Class3>
				</Team2>
			</Game>
			<Game>
				<GameID>3</GameID>
				<Team1>
					<Player1></Player1>
					<Class1></Class1>
					<Player2></Player2>
					<Class2></Class2>
					<Player3></Player3>
					<Class3></Class3>
				</Team1>
				<Team2>
					<Player1></Player1>
					<Class1></Class1>
					<Player2></Player2>
					<Class2></Class2>
					<Player3></Player3>
					<Class3></Class3>
				</Team2>
			</Game>
			<Game>
				<GameID>4</GameID>
				<Team1>
					<Player1></Player1>
					<Class1></Class1>
					<Player2></Player2>
					<Class2></Class2>
					<Player3></Player3>
					<Class3></Class3>
				</Team1>
				<Team2>
					<Player1></Player1>
					<Class1></Class1>
					<Player2></Player2>
					<Class2></Class2>
					<Player3></Player3>
					<Class3></Class3>
				</Team2>
			</Game>
			<Game>
				<GameID>5</GameID>
				<Team1>
					<Player1></Player1>
					<Class1></Class1>
					<Player2></Player2>
					<Class2></Class2>
					<Player3></Player3>
					<Class3></Class3>
				</Team1>
				<Team2>
					<Player1></Player1>
					<Class1></Class1>
					<Player2></Player2>
					<Class2></Class2>
					<Player3></Player3>
					<Class3></Class3>
				</Team2>
			</Game>
		
		
		</Games>
		
	</Match>

</Tournament_Data>